BibUtils/__init__.py
BibUtils/image_work.py
utilsbib-32.7.dist-info/LICENSE
utilsbib-32.7.dist-info/METADATA
utilsbib-32.7.dist-info/WHEEL
utilsbib-32.7.dist-info/top_level.txt
utilsbib-32.7.dist-info/RECORD
