Metadata-Version: 2.1
Name: utilsbib
Version: 32.7
Summary: An recurrent utility algorithm package
Home-page: https://github.com/Bibjuju/utils-bib
Author: Habibou Sissoko
Author-email: habibou.s@outlook.fr
License: UNKNOWN
Platform: UNKNOWN
Classifier: Programming Language :: Python :: 3
Classifier: License :: OSI Approved :: MIT License
Classifier: Operating System :: OS Independent
